README.txt
setup.py
django_mediagenie.egg-info/PKG-INFO
django_mediagenie.egg-info/SOURCES.txt
django_mediagenie.egg-info/dependency_links.txt
django_mediagenie.egg-info/top_level.txt
mediagenie/__init__.py
mediagenie/bundle.py
mediagenie/bundles.py
mediagenie/env.py
mediagenie/generate.py
mediagenie/loading.py
mediagenie/stream.py
mediagenie/transform.py
mediagenie/urls.py
mediagenie/views.py
mediagenie/contrib/__init__.py
mediagenie/contrib/jinja2ext.py
mediagenie/generators/__init__.py
mediagenie/generators/images.py
mediagenie/management/__init__.py
mediagenie/management/commands/__init__.py
mediagenie/management/commands/gm.py
mediagenie/management/commands/watch_media.py
mediagenie/templatetags/__init__.py
mediagenie/templatetags/media.py
mediagenie/transforms/__init__.py
mediagenie/transforms/concat.py
mediagenie/transforms/css_compressor.py
mediagenie/transforms/scss.py
mediagenie/transforms/uglifyjs.py
mediagenie/transforms/write.py