Metadata-Version: 1.1
Name: django-mediagenie
Version: 0.1.4
Summary: Static files management for Django
Home-page: https://github.com/mcamac/django-media-genie
Author: Martin Camacho
Author-email: martin@kensho.com
License: MIT
Download-URL: https://github.com/mcamac/django-media-genie/tarball/0.1.4
Platform: UNKNOWN
